Metadata-Version: 1.1
Name: getstmpy
Version: 0.1.1
Summary: Scanning tunneling microscopy data analysis suite
Home-page: https://github.com/harrispirie/stmpy
Author: Harris Pirie
Author-email: hpirie@live.com
License: MIT
Download-URL: https://github.com/harrispirie/stmpy/archive/v0.1.tar.gz
Keywords: STM,Python,Data Analysis
Platform: UNKNOWN
Classifier: Development Status :: 3 - Alpha
Classifier: Intended Audience :: Developers
Classifier: Topic :: Software Development :: Build Tools
Classifier: License :: OSI Approved :: MIT License
Classifier: Programming Language :: Python :: 3
